quasar/TODO
quasar/__init__.py
quasar/algebra.py
quasar/backend.py
quasar/circuit.py
quasar/davidson.py
quasar/format.py
quasar/index_allocator.py
quasar/measurement.py
quasar/observable.py
quasar/old_measurement.py
quasar/old_tomography.py
quasar/optimizer.py
quasar/options.py
quasar/parameters.py
quasar/pauli.py
quasar/quasar_backend.py
quasar/transpiler.py
quasar/testing_strategies/__init__.py
quasar/testing_strategies/circuits.py
qcware_quasar-1.0.7.dist-info/LICENSE.txt
qcware_quasar-1.0.7.dist-info/WHEEL
qcware_quasar-1.0.7.dist-info/METADATA
qcware_quasar-1.0.7.dist-info/RECORD
