Metadata-Version: 2.1
Name: qcware-quasar
Version: 1.0.7
Summary: Build and execute quantum circuits on various backends.
Home-page: http://github.com/qcware/quasar
Author: Rob Parrish
Author-email: rob.parrish@qcware.com
Classifier: License :: OSI Approved :: Apache Software License
Classifier: Programming Language :: Python :: 3
Classifier: Operating System :: OS Independent
Requires-Dist: numpy >= 1.18.4
Requires-Dist: scipy >= 1.3.3
Requires-Dist: sortedcontainers>=2.3.0
Requires-Dist: cirq == 0.5.0 ; extra == "cirq"
Requires-Dist: requests >= 2.22.0 ; extra == "ionq"
Requires-Dist: pyquil==2.16.0 ; extra == "pyquil"
Requires-Dist: qiskit-aer >= 0.5.1 ; extra == "qiskit"
Requires-Dist: hypothesis[numpy] >= 6.8.0 ; extra == "test"
Provides-Extra: cirq
Provides-Extra: ionq
Provides-Extra: pyquil
Provides-Extra: qiskit
Provides-Extra: test
